pyrotor/__init__.py
pyrotor/basis.py
pyrotor/constraints.py
pyrotor/cost_functions.py
pyrotor/data_analysis.py
pyrotor/datasets.py
pyrotor/iterations.py
pyrotor/linear_conditions.py
pyrotor/log.py
pyrotor/objective_matrices.py
pyrotor/optimization.py
pyrotor/projection.py
pyrotor/pyrotor.py
pyrotor/toy_dataset/example_1/trajectory_0.csv
pyrotor/toy_dataset/example_1/trajectory_1.csv
pyrotor/toy_dataset/example_1/trajectory_10.csv
pyrotor/toy_dataset/example_1/trajectory_100.csv
pyrotor/toy_dataset/example_1/trajectory_101.csv
pyrotor/toy_dataset/example_1/trajectory_102.csv
pyrotor/toy_dataset/example_1/trajectory_103.csv
pyrotor/toy_dataset/example_1/trajectory_104.csv
pyrotor/toy_dataset/example_1/trajectory_105.csv
pyrotor/toy_dataset/example_1/trajectory_106.csv
pyrotor/toy_dataset/example_1/trajectory_107.csv
pyrotor/toy_dataset/example_1/trajectory_108.csv
pyrotor/toy_dataset/example_1/trajectory_109.csv
pyrotor/toy_dataset/example_1/trajectory_11.csv
pyrotor/toy_dataset/example_1/trajectory_110.csv
pyrotor/toy_dataset/example_1/trajectory_111.csv
pyrotor/toy_dataset/example_1/trajectory_112.csv
pyrotor/toy_dataset/example_1/trajectory_113.csv
pyrotor/toy_dataset/example_1/trajectory_114.csv
pyrotor/toy_dataset/example_1/trajectory_115.csv
pyrotor/toy_dataset/example_1/trajectory_116.csv
pyrotor/toy_dataset/example_1/trajectory_117.csv
pyrotor/toy_dataset/example_1/trajectory_118.csv
pyrotor/toy_dataset/example_1/trajectory_119.csv
pyrotor/toy_dataset/example_1/trajectory_12.csv
pyrotor/toy_dataset/example_1/trajectory_120.csv
pyrotor/toy_dataset/example_1/trajectory_121.csv
pyrotor/toy_dataset/example_1/trajectory_13.csv
pyrotor/toy_dataset/example_1/trajectory_14.csv
pyrotor/toy_dataset/example_1/trajectory_15.csv
pyrotor/toy_dataset/example_1/trajectory_16.csv
pyrotor/toy_dataset/example_1/trajectory_17.csv
pyrotor/toy_dataset/example_1/trajectory_18.csv
pyrotor/toy_dataset/example_1/trajectory_19.csv
pyrotor/toy_dataset/example_1/trajectory_2.csv
pyrotor-1.0.4.dist-info/LICENSE
pyrotor-1.0.4.dist-info/METADATA
pyrotor-1.0.4.dist-info/WHEEL
pyrotor-1.0.4.dist-info/top_level.txt
pyrotor-1.0.4.dist-info/RECORD
