Metadata-Version: 2.1
Name: pyrotor
Version: 1.0.4
Summary: Trajectory optimization package based on data
Home-page: https://github.com/bguedj/pyrotor
Author-email: arthur.talpaert@isen.yncrea.fr
License: MIT
License-File: LICENSE
Requires-Dist: cvxopt (>=1.2.7)
Requires-Dist: numpy (>=1.24.1)
Requires-Dist: pandas (>=1.5.2)
Requires-Dist: scipy (>=1.5.4)
Requires-Dist: mock
Requires-Dist: pytest
Requires-Dist: pickleshare (>=0.7.5)
Requires-Dist: scikit-learn (>=1.2.0)
Requires-Dist: sphinx
Requires-Dist: sphinx-rtd-theme
